pandas_datapackage_reader/__init__.py
pandas_datapackage_reader/_version.py
pandas_datapackage_reader-0.18.0.dist-info/LICENSE
pandas_datapackage_reader-0.18.0.dist-info/METADATA
pandas_datapackage_reader-0.18.0.dist-info/WHEEL
pandas_datapackage_reader-0.18.0.dist-info/top_level.txt
pandas_datapackage_reader-0.18.0.dist-info/RECORD
