Metadata-Version: 2.1
Name: pandas-datapackage-reader
Version: 0.18.0
Summary: Pandas Data Package Reader
Home-page: https://github.com/rgieseke/pandas-datapackage-reader
Author: Robert Gieseke
Author-email: robert.gieseke@pik-potsdam.de
License: BSD
Keywords: data-package
Platform: any
Classifier: Development Status :: 4 - Beta
Classifier: Intended Audience :: Developers
Classifier: Operating System :: OS Independent
Classifier: Programming Language :: Python :: 3.6
Classifier: Programming Language :: Python :: 3.7
Requires-Dist: pandas (>=0.24.0)
Requires-Dist: requests
Provides-Extra: tests
Requires-Dist: pytest (>=4.1) ; extra == 'tests'
Requires-Dist: geopandas ; extra == 'tests'
